{
  "header": {
    "menu": {
      "about": "About Me",
      "projects": "My Projects",
      "skills": "Skills",
      "contact": "Get In Touch"
    }
  },
  "introducing": {
    "title": "Hi I'm Felix Web Developer",
    "description": "I enjoy developing, creating & solving problems",
    "button": "Download Resume"
  },
  "about": {
    "title": "About Me",
    "description": "Over the recent years I've developed different projects in order to improve my skills as a Frontend Developer, collab with teammates & more. Right now I'm offerring my skills on development to solve your needs"
  },
  "portfolio": {
    "title": "Portfolio",
    "button":"Show More"
  }
}