{
  "header": {
    "menu": {
      "about": "Sobre mí",
      "projects": "Proyectos",
      "skills": "Herramientas",
      "contact": "Contáctame!"
    }
  },
  "introducing": {
    "title": "Hola! Soy Félix Programador Web",
    "description": "Me divierto programando, creando y sobre todo resolviendo problemas",
    "button": "Descargar CV"
  },
  "about": {
    "title": "Sobre Mí",
    "description": "Durante los últimos años he desarrollado diferentes proyectos para mejorar mis habilidades como Programador Frontend, colaborar con compañeros y mucho más. Ahora mi objetivo es ofrecer mis habilidades en desarrollo para satisfacer tus necesidades"
  },
  "portfolio": {
    "title": "Portafolio",
    "techStack": "Tecnologías",
    "details": "Detalles",
    "watchLive": "Ver Sitio",
    "button":"Mostrar Más",
    "projects": {
      "petvet": {
        "title": "petvet",
        "short_description": "petvet desc corta",
        "github": "Mira este proyecto en GitHub",
        "description": "petvet description",
        "author": "Felix Reyna",
        "collab": "none"
      },
      "bambina": {
        "title": "Bambina",
        "short_description": "Bambina desc corta",
        "github": "Mira este proyecto en GitHub",
        "description": "Bambina description",
        "author": "Shakira Contreras",
        "collab": "Felix Reyna"
      },
      "figram": {
        "title": "figram",
        "short_description": "Figram desc corta",
        "github": "Mira este proyecto en GitHub",
        "description": "Figram description",
        "author": "Felix Reyna",
        "collab": "none"
      },
      "figuitars": {
        "title": "Figuitars",
        "short_description": "Figuitars desc corta",
        "github": "Mira este proyecto en GitHub",
        "description": "Figuitars description",
        "author": "Felix Reyna",
        "collab": "none"
      },
      "mystarwars": {
        "title": "My Star Wars",
        "short_description": "My Star Wars desc corta",
        "github": "Mira este proyecto en GitHub",
        "description": "My Star Wars description",
        "author": "Felix Reyna",
        "collab": "none"
      },
      "fitimer": {
        "title": "Fitimer",
        "short_description": "Fitimer desc corta",
        "github": "Mira este proyecto en GitHub",
        "description": "Fitimer description",
        "author": "Felix Reyna",
        "collab": "none"
      },
      "paintit": {
        "title": "Paint It",
        "short_description": "Paint It desc corta",
        "github": "Mira este proyecto en GitHub",
        "description": "Paint It description",
        "author": "Felix Reyna",
        "collab": "none"
      }
    }
  },
  "skills": {
    "title": "Tecnologías",
    "html": "HTML",
    "css": "CSS",
    "sass": "Sass",
    "tailwind": "Tailwind",
    "javaScript": "JavaScript",
    "typeScript": "TypeScript",
    "react": "React",
    "nextjs": "NextJS",
    "webpack": "Webpack",
    "vite": "Vite",
    "shopify": "Shopify"
  },
  "contact": {
    "title": "Contáctame!",
    "description": "¡Hola! Si quieres que te ayude con tu sitio web no dudes en contactarme, así que por favor ",
    "email": "Envíame un E-mail"
  },
  "footer": {
    "title": "¿Quieres saber más de mi?",
    "description": "Soy Ing. Telecomunicaciones y actualmente soy profesor universitario, mi pasión por la tecnología me ha permitido explorar distintos ámbitos y hasta ahora mi favorito es el desarrollo web.",
    "explore": "Explorar",
    "links": {
      "about": "Sobre mí",
      "projects": "Proyectos",
      "skills": "Herramientas",
      "contact": "Contáctame!"
    },
    "data": "Dirección",
    "dataDescription": "Resido en Valencia, Carabobo, Venezuela. Mi Email: felixreyna48@gmail.com",
    "email":"Envíame un E-mail",
    "form": {
      "address": "Tu dirección de correo",
      "subject": "Asunto",
      "message": "Mensaje",
      "send": "Enviar"
    }
  }
}